{
"meta":{"test_sets":[],"test_metrics":[],"learn_metrics":[{"best_value":"Min","name":"RMSE"}],"launch_mode":"Train","parameters":"","iteration_count":100,"learn_sets":["learn"],"name":"experiment"},
"iterations":[
{"learn":[15.00758229],"iteration":0,"passed_time":0.001788147006,"remaining_time":0.1770265535},
{"learn":[14.16711093],"iteration":1,"passed_time":0.003117231501,"remaining_time":0.1527443435},
{"learn":[13.48566506],"iteration":2,"passed_time":0.00452117444,"remaining_time":0.1461846402},
{"learn":[12.77618312],"iteration":3,"passed_time":0.005968564921,"remaining_time":0.1432455581},
{"learn":[12.16352498],"iteration":4,"passed_time":0.00741977973,"remaining_time":0.1409758149},
{"learn":[11.49931505],"iteration":5,"passed_time":0.008699760369,"remaining_time":0.1362962458},
{"learn":[11.03194409],"iteration":6,"passed_time":0.009977061487,"remaining_time":0.1325523883},
{"learn":[10.60211177],"iteration":7,"passed_time":0.01134877501,"remaining_time":0.1305109126},
{"learn":[10.2174615],"iteration":8,"passed_time":0.01282570757,"remaining_time":0.1296821543},
{"learn":[9.817477191],"iteration":9,"passed_time":0.01427292393,"remaining_time":0.1284563154},
{"learn":[9.361318532],"iteration":10,"passed_time":0.01573496361,"remaining_time":0.1273101601},
{"learn":[8.98948442],"iteration":11,"passed_time":0.01697116855,"remaining_time":0.1244552361},
{"learn":[8.663599452],"iteration":12,"passed_time":0.01835064235,"remaining_time":0.1228081449},
{"learn":[8.41489027],"iteration":13,"passed_time":0.0196741535,"remaining_time":0.1208555143},
{"learn":[8.117654892],"iteration":14,"passed_time":0.02095815565,"remaining_time":0.118762882},
{"learn":[7.897812478],"iteration":15,"passed_time":0.02239003638,"remaining_time":0.117547691},
{"learn":[7.645792353],"iteration":16,"passed_time":0.02386087919,"remaining_time":0.1164972337},
{"learn":[7.377771496],"iteration":17,"passed_time":0.02521818014,"remaining_time":0.1148828207},
{"learn":[7.187481638],"iteration":18,"passed_time":0.02670853152,"remaining_time":0.113862687},
{"learn":[6.964821099],"iteration":19,"passed_time":0.02803607312,"remaining_time":0.1121442925},
{"learn":[6.804316582],"iteration":20,"passed_time":0.02936335241,"remaining_time":0.1104621353},
{"learn":[6.657891664],"iteration":21,"passed_time":0.03095488681,"remaining_time":0.1097491441},
{"learn":[6.488821113],"iteration":22,"passed_time":0.0324589766,"remaining_time":0.1086670086},
{"learn":[6.359750175],"iteration":23,"passed_time":0.03382472314,"remaining_time":0.1071116233},
{"learn":[6.238061178],"iteration":24,"passed_time":0.03537718198,"remaining_time":0.1061315459},
{"learn":[6.151033675],"iteration":25,"passed_time":0.03695686464,"remaining_time":0.1051849224},
{"learn":[6.038479623],"iteration":26,"passed_time":0.0382770969,"remaining_time":0.1034899286},
{"learn":[5.936238438],"iteration":27,"passed_time":0.03972115639,"remaining_time":0.1021401164},
{"learn":[5.8456006],"iteration":28,"passed_time":0.04107481681,"remaining_time":0.1005624825},
{"learn":[5.737686896],"iteration":29,"passed_time":0.04261102366,"remaining_time":0.09942572186},
{"learn":[5.659194723],"iteration":30,"passed_time":0.04406439488,"remaining_time":0.09807881441},
{"learn":[5.58738397],"iteration":31,"passed_time":0.04546352123,"remaining_time":0.09660998261},
{"learn":[5.507729433],"iteration":32,"passed_time":0.04690551286,"remaining_time":0.09523240489},
{"learn":[5.450817922],"iteration":33,"passed_time":0.04835240404,"remaining_time":0.09386054903},
{"learn":[5.387058251],"iteration":34,"passed_time":0.0498331055,"remaining_time":0.09254719592},
{"learn":[5.328986118],"iteration":35,"passed_time":0.05155500373,"remaining_time":0.09165333996},
{"learn":[5.265411028],"iteration":36,"passed_time":0.05289514227,"remaining_time":0.09006470171},
{"learn":[5.192831073],"iteration":37,"passed_time":0.05414166535,"remaining_time":0.08833640136},
{"learn":[5.14250658],"iteration":38,"passed_time":0.05562518473,"remaining_time":0.08700349406},
{"learn":[5.092689255],"iteration":39,"passed_time":0.05705302869,"remaining_time":0.08557954304},
{"learn":[5.048649435],"iteration":40,"passed_time":0.05839630513,"remaining_time":0.08403370738},
{"learn":[5.012450652],"iteration":41,"passed_time":0.05988149577,"remaining_time":0.08269349415},
{"learn":[4.940703301],"iteration":42,"passed_time":0.06123796853,"remaining_time":0.08117591177},
{"learn":[4.905737875],"iteration":43,"passed_time":0.06260049236,"remaining_time":0.07967335391},
{"learn":[4.85102905],"iteration":44,"passed_time":0.06408749043,"remaining_time":0.07832915497},
{"learn":[4.802231071],"iteration":45,"passed_time":0.06540874843,"remaining_time":0.07678418294},
{"learn":[4.75889769],"iteration":46,"passed_time":0.06681354448,"remaining_time":0.07534293314},
{"learn":[4.71003427],"iteration":47,"passed_time":0.06823270511,"remaining_time":0.07391876387},
{"learn":[4.678119441],"iteration":48,"passed_time":0.06981735393,"remaining_time":0.07266704185},
{"learn":[4.656299575],"iteration":49,"passed_time":0.07145035394,"remaining_time":0.07145035394},
{"learn":[4.615654342],"iteration":50,"passed_time":0.07291855555,"remaining_time":0.07005900435},
{"learn":[4.576649143],"iteration":51,"passed_time":0.07441634277,"remaining_time":0.06869200871},
{"learn":[4.546696316],"iteration":52,"passed_time":0.07616007453,"remaining_time":0.0675381793},
{"learn":[4.511208816],"iteration":53,"passed_time":0.07754703476,"remaining_time":0.06605858516},
{"learn":[4.47117809],"iteration":54,"passed_time":0.07898434113,"remaining_time":0.06462355183},
{"learn":[4.446859918],"iteration":55,"passed_time":0.08039279111,"remaining_time":0.06316576444},
{"learn":[4.416572951],"iteration":56,"passed_time":0.08190727233,"remaining_time":0.06178969667},
{"learn":[4.397281594],"iteration":57,"passed_time":0.08330713199,"remaining_time":0.0603258542},
{"learn":[4.352635313],"iteration":58,"passed_time":0.08495515883,"remaining_time":0.0590366358},
{"learn":[4.322362721],"iteration":59,"passed_time":0.08649024989,"remaining_time":0.05766016659},
{"learn":[4.295192405],"iteration":60,"passed_time":0.08769775694,"remaining_time":0.05606905772},
{"learn":[4.267004296],"iteration":61,"passed_time":0.08922685126,"remaining_time":0.05468742496},
{"learn":[4.245843368],"iteration":62,"passed_time":0.09057790136,"remaining_time":0.05319654524},
{"learn":[4.218336241],"iteration":63,"passed_time":0.09191235866,"remaining_time":0.05170070175},
{"learn":[4.172337945],"iteration":64,"passed_time":0.09343512214,"remaining_time":0.05031121961},
{"learn":[4.144919695],"iteration":65,"passed_time":0.0949499155,"remaining_time":0.04891359283},
{"learn":[4.112943118],"iteration":66,"passed_time":0.09634752908,"remaining_time":0.04745475313},
{"learn":[4.090063308],"iteration":67,"passed_time":0.09756561173,"remaining_time":0.04591322905},
{"learn":[4.068095008],"iteration":68,"passed_time":0.09902799555,"remaining_time":0.04449083858},
{"learn":[4.043827311],"iteration":69,"passed_time":0.100469822,"remaining_time":0.04305849514},
{"learn":[4.019026387],"iteration":70,"passed_time":0.1019298314,"remaining_time":0.04163331141},
{"learn":[4.006265834],"iteration":71,"passed_time":0.1033653798,"remaining_time":0.0401976477},
{"learn":[3.976316683],"iteration":72,"passed_time":0.1048078819,"remaining_time":0.03876455905},
{"learn":[3.951833528],"iteration":73,"passed_time":0.106299121,"remaining_time":0.0373483398},
{"learn":[3.93839902],"iteration":74,"passed_time":0.1078396124,"remaining_time":0.03594653746},
{"learn":[3.914100335],"iteration":75,"passed_time":0.1093978935,"remaining_time":0.0345467032},
{"learn":[3.880254992],"iteration":76,"passed_time":0.1107357856,"remaining_time":0.03307692296},
{"learn":[3.879287517],"iteration":77,"passed_time":0.1111054658,"remaining_time":0.03133743908},
{"learn":[3.866877753],"iteration":78,"passed_time":0.1124327912,"remaining_time":0.02988719767},
{"learn":[3.852891352],"iteration":79,"passed_time":0.1139317363,"remaining_time":0.02848293407},
{"learn":[3.823505377],"iteration":80,"passed_time":0.1152668718,"remaining_time":0.02703790821},
{"learn":[3.805833218],"iteration":81,"passed_time":0.1166810846,"remaining_time":0.025612921},
{"learn":[3.786881046],"iteration":82,"passed_time":0.1180333914,"remaining_time":0.02417551391},
{"learn":[3.763806981],"iteration":83,"passed_time":0.119404282,"remaining_time":0.02274367276},
{"learn":[3.739882148],"iteration":84,"passed_time":0.1207395995,"remaining_time":0.02130698814},
{"learn":[3.725463411],"iteration":85,"passed_time":0.1221568336,"remaining_time":0.01988599617},
{"learn":[3.709937447],"iteration":86,"passed_time":0.1235252065,"remaining_time":0.01845778947},
{"learn":[3.693327464],"iteration":87,"passed_time":0.1250560122,"remaining_time":0.01705309258},
{"learn":[3.683657114],"iteration":88,"passed_time":0.126517473,"remaining_time":0.01563699105},
{"learn":[3.662972839],"iteration":89,"passed_time":0.1278602111,"remaining_time":0.01420669012},
{"learn":[3.652354234],"iteration":90,"passed_time":0.1294884507,"remaining_time":0.01280655007},
{"learn":[3.63538258],"iteration":91,"passed_time":0.1310420026,"remaining_time":0.01139495675},
{"learn":[3.61306987],"iteration":92,"passed_time":0.1324898109,"remaining_time":0.009972351359},
{"learn":[3.598886851],"iteration":93,"passed_time":0.1339349921,"remaining_time":0.008549042052},
{"learn":[3.591626364],"iteration":94,"passed_time":0.1355189196,"remaining_time":0.007132574713},
{"learn":[3.581942952],"iteration":95,"passed_time":0.1371770327,"remaining_time":0.005715709697},
{"learn":[3.564583224],"iteration":96,"passed_time":0.13863444,"remaining_time":0.004287663092},
{"learn":[3.544354217],"iteration":97,"passed_time":0.1400656733,"remaining_time":0.002858483129},
{"learn":[3.524398658],"iteration":98,"passed_time":0.1414415635,"remaining_time":0.001428702662},
{"learn":[3.50074282],"iteration":99,"passed_time":0.1430785646,"remaining_time":0}
]}